utilwise/__init__.py
utilwise-0.0.1.dist-info/LICENSE
utilwise-0.0.1.dist-info/METADATA
utilwise-0.0.1.dist-info/WHEEL
utilwise-0.0.1.dist-info/top_level.txt
utilwise-0.0.1.dist-info/RECORD
