Metadata-Version: 2.1
Name: utilwise
Version: 0.0.1
Summary: Collection of utilities built native from Python
Author-email: Brian Wisniewski <brianwisniewski44@gmail.com>
Project-URL: Project Home, https://github.com/brianwisniewski44/utilwise
Classifier: Programming Language :: Python :: 3
Classifier: License :: OSI Approved :: MIT License
Classifier: Operating System :: OS Independent
Requires-Python: >=3.8
License-File: LICENSE
